finely/main.py
finely-1.0.2.dist-info/licenses/LICENSE
finely-1.0.2.dist-info/METADATA
finely-1.0.2.dist-info/WHEEL
finely-1.0.2.dist-info/entry_points.txt
finely-1.0.2.dist-info/top_level.txt
finely-1.0.2.dist-info/RECORD
