Metadata-Version: 2.4
Name: finely
Version: 1.0.2
Summary: A beautiful personal finance dashboard built with Flet
Author-email: Amir Ansarpour <amir.ansarpour2003@gmail.com>
License: MIT
Requires-Python: >=3.9
License-File: LICENSE
Requires-Dist: flet>=0.28.0
Requires-Dist: matplotlib>=3.10.0
Provides-Extra: dev
Requires-Dist: flet-cli; extra == "dev"
Requires-Dist: watchdog; extra == "dev"
Dynamic: license-file
